alphavantage_mcp_server/__init__.py
alphavantage_mcp_server/api.py
alphavantage_mcp_server/oauth.py
alphavantage_mcp_server/prompts.py
alphavantage_mcp_server/response_utils.py
alphavantage_mcp_server/server.py
alphavantage_mcp_server/telemetry_bootstrap.py
alphavantage_mcp_server/telemetry_instrument.py
alphavantage_mcp_server/tools.py
alphavantage_mcp-0.3.24.dist-info/METADATA
alphavantage_mcp-0.3.24.dist-info/WHEEL
alphavantage_mcp-0.3.24.dist-info/entry_points.txt
alphavantage_mcp-0.3.24.dist-info/licenses/LICENSE
alphavantage_mcp-0.3.24.dist-info/RECORD
