Metadata-Version: 2.4
Name: alphavantage-mcp
Version: 0.3.24
Summary: AlphaVantage MCP server - Financial data tools for Model Context Protocol
Project-URL: Homepage, https://github.com/calvernaz/alphavantage
Project-URL: Repository, https://github.com/calvernaz/alphavantage
Project-URL: Issues, https://github.com/calvernaz/alphavantage/issues
Project-URL: Documentation, https://github.com/calvernaz/alphavantage#readme
Author-email: Cesar Alvernaz <cesar.alvernaz@gmail.com>
License: MIT
License-File: LICENSE
Keywords: alphavantage,api,financial,mcp,server,stocks
Classifier: Development Status :: 4 - Beta
Classifier: Intended Audience :: Developers
Classifier: License :: OSI Approved :: MIT License
Classifier: Programming Language :: Python :: 3
Classifier: Programming Language :: Python :: 3.12
Classifier: Topic :: Office/Business :: Financial
Classifier: Topic :: Software Development :: Libraries :: Python Modules
Requires-Python: >=3.12
Requires-Dist: httpx>=0.28.1
Requires-Dist: mcp>=1.9.4
Requires-Dist: packaging>=21.0
Requires-Dist: prometheus-client>=0.20.0
Requires-Dist: pyjwt>=2.10.1
Requires-Dist: starlette>=0.47.2
Requires-Dist: toml>=0.10.2
Requires-Dist: uvicorn>=0.32.1
